patternsum/__init__.py
patternsum/data.py
patternsum/util.py
patternsum/core/__init__.py
patternsum/core/hook.py
patternsum/core/species.py
patternsum/core/summarization.py
patternsum/optimizer/__init__.py
patternsum/optimizer/optimizer.py
patternsum/optimizer/score.py
patternsum/pattern/__init__.py
patternsum/pattern/pattern.py
patternsum/pattern/word_sequence.py
patternsum-1.1.1.dist-info/LICENSE.txt
patternsum-1.1.1.dist-info/METADATA
patternsum-1.1.1.dist-info/WHEEL
patternsum-1.1.1.dist-info/top_level.txt
patternsum-1.1.1.dist-info/RECORD
