Metadata-Version: 2.1
Name: patternsum
Version: 1.1.1
Summary: An algorithm to summarize possible patterns covered in a list of strings using Genetic Algorithm.
Home-page: https://github.com/SSripilaipong/patternsum
Author: SSripilaipong
Author-email: SHSnail@mail.com
License: UNKNOWN
Platform: UNKNOWN
Classifier: Programming Language :: Python :: 3
Classifier: License :: OSI Approved :: MIT License
Classifier: Operating System :: OS Independent
Requires-Python: >=3.6
Requires-Dist: numpy
Requires-Dist: pandas
